ospeak/__init__.py
ospeak/__main__.py
ospeak/cli.py
ospeak-0.3.dist-info/LICENSE
ospeak-0.3.dist-info/METADATA
ospeak-0.3.dist-info/WHEEL
ospeak-0.3.dist-info/entry_points.txt
ospeak-0.3.dist-info/top_level.txt
ospeak-0.3.dist-info/RECORD
