Metadata-Version: 2.1
Name: ospeak
Version: 0.3
Summary: CLI tool for running text through OpenAI Text to speech
Author: Simon Willison
License: Apache-2.0
Project-URL: Homepage, https://github.com/simonw/ospeak
Project-URL: Changelog, https://github.com/simonw/ospeak/releases
Project-URL: Issues, https://github.com/simonw/ospeak/issues
Project-URL: CI, https://github.com/simonw/ospeak/actions
Classifier: License :: OSI Approved :: Apache Software License
Requires-Python: >=3.8
License-File: LICENSE
Requires-Dist: click
Requires-Dist: openai >=1.0
Requires-Dist: pydub
Requires-Dist: simpleaudio ; sys_platform == "darwin"
Provides-Extra: test
Requires-Dist: pytest ; extra == 'test'
Requires-Dist: cogapp ; extra == 'test'
